LICENSE
README.md
setup.cfg
setup.py
src/pyouter/__init__.py
src/pyouter/__main__.py
src/pyouter/app.py
src/pyouter/default.py
src/pyouter/errors.py
src/pyouter/executor.py
src/pyouter/router.py
src/pyouter.egg-info/PKG-INFO
src/pyouter.egg-info/SOURCES.txt
src/pyouter.egg-info/dependency_links.txt
src/pyouter.egg-info/entry_points.txt
src/pyouter.egg-info/top_level.txt
src/pyouter/bash/__init__.py
src/pyouter/bash/install.py
src/pyouter/fish/__init__.py
src/pyouter/fish/install.py
src/pyouter/oh_my_zsh/__init__.py
src/pyouter/oh_my_zsh/install.py
src/tests/__init__.py
src/tests/test.py
src/tests/test_async.py
src/tests/test_router_tree_view.py