Metadata-Version: 2.1
Name: pyouter
Version: 0.1.1
Summary: Python command line tasks router
Home-page: https://github.com/fanfeilong/pyouter
Author: Fan Fei Long, Liu xin
Author-email: fanfeilong@gmail.com
License: MIT
Classifier: Topic :: Utilities
Classifier: Programming Language :: Python :: 3.5
Classifier: Programming Language :: Python :: 3.6
Classifier: Programming Language :: Python :: 3.7
Classifier: Programming Language :: Python :: 3.8
Classifier: Programming Language :: Python :: 3.9
Classifier: Programming Language :: Python :: 3.10
Classifier: Programming Language :: Python :: 3 :: Only
Classifier: License :: OSI Approved :: MIT License
License-File: LICENSE
